cutepy32/__init__.py
cutepy32/colorizing.py
cutepy32/term_colors.py
tests/__init__.py
tests/tests_grab.py
cutepy32-0.0.1.dist-info/METADATA
cutepy32-0.0.1.dist-info/WHEEL
cutepy32-0.0.1.dist-info/top_level.txt
cutepy32-0.0.1.dist-info/RECORD
