Metadata-Version: 2.1
Name: cutepy32
Version: 0.0.1
Summary: Terminal colors & useful modules installer
Author: patchthisloserrr
Author-email: test@gmail.com
Keywords: python,python system Detection,python hex,python rgb,python hex,python loader,rich python,python rich,cutepy
Requires-Dist: WMI
Requires-Dist: guardshield
Requires-Dist: pywin32
Requires-Dist: discord
Requires-Dist: pycryptodome
